README.rst
setup.py
builders/__init__.py
builders/builder.py
builders/construct.py
builders/info.py
builders/logger.py
builders/modifiers.py
builders.egg-info/PKG-INFO
builders.egg-info/SOURCES.txt
builders.egg-info/dependency_links.txt
builders.egg-info/top_level.txt