Metadata-Version: 1.1
Name: builders
Version: 1.2.8
Summary: Lightweight test data generation framework
Home-page: http://github.com/yandex-qatools/builders
Author: Ivan Kalinin
Author-email: pupssman@yandex-team.ru
License: Apache License, Version 2.0
Platform: UNKNOWN
Classifier: Development Status :: 5 - Production/Stable
Classifier: Environment :: Console
Classifier: Intended Audience :: Developers
Classifier: License :: OSI Approved :: Apache Software License
Classifier: Operating System :: OS Independent
Classifier: Programming Language :: Python
Classifier: Topic :: Software Development
Classifier: Topic :: Software Development :: Quality Assurance
Classifier: Topic :: Software Development :: Testing
